iot_dqa/__init__.py
iot_dqa/dimensions.py
iot_dqa/dq_score.py
iot_dqa/utils/__init__.py
iot_dqa/utils/configs.py
iot_dqa/utils/enums.py
iot_dqa/utils/exceptions.py
iot_dqa/utils/logger.py
iot_dqa-0.0.6.dist-info/LICENSE
iot_dqa-0.0.6.dist-info/METADATA
iot_dqa-0.0.6.dist-info/WHEEL
iot_dqa-0.0.6.dist-info/RECORD
