Metadata-Version: 2.1
Name: iot-dqa
Version: 0.0.6
Summary: Fast and efficient data quality assessment for IoT timeseries data.
License: LICENSE
Keywords: IoT,Data Quality,Data Quality Assessment,Outlier Detection
Author: Emmanuel Jolaiya
Author-email: jolaiyaemmanuel@gmail.com
Requires-Python: >=3.9.1,<4.0.0
Classifier: Intended Audience :: Information Technology
Classifier: Intended Audience :: Science/Research
Classifier: License :: Other/Proprietary License
Classifier: Programming Language :: Python :: 3
Classifier: Programming Language :: Python :: 3.10
Classifier: Programming Language :: Python :: 3.11
Classifier: Programming Language :: Python :: 3.12
Classifier: Programming Language :: Python :: 3 :: Only
Classifier: Programming Language :: Python :: 3.8
Classifier: Programming Language :: Python :: 3.9
Classifier: Topic :: Scientific/Engineering :: GIS
Classifier: Topic :: Software Development :: Libraries :: Python Modules
Requires-Dist: optuna (>=4.2.1,<5.0.0)
Requires-Dist: polars (>=1.26.0,<2.0.0)
Requires-Dist: scikit-learn (>=1.6.1,<2.0.0)
Project-URL: Bug Tracker, https://github.com/jeafreezy/iot-dqa/issues
Project-URL: Documentation, https://jeafreezy.github.io/iot-dqa/latest/
Project-URL: Homepage, https://jeafreezy.github.io/iot-dqa/latest/
Project-URL: Repository, https://github.com/jeafreezy/iot-dqa
